{
  "ComponentIndexes": {
    "Component1": 9
  },
  "ControlUniqueGuids": {},
  "ControlUniqueIds": {
    "1 Project Client_DataCard1": 132,
    "1 Project Description_DataCard1": 152,
    "1 Project End Date_DataCard1": 147,
    "1 Project Role_DataCard1": 137,
    "1 Project Start Date_DataCard1": 142,
    "1 Project Title_DataCard1": 127,
    "1ProjectClient": 406,
    "1ProjectClient_1": 315,
    "1ProjectDescription": 413,
    "1ProjectDescription_1": 322,
    "1ProjectEndDate": 412,
    "1ProjectEndDate_1": 321,
    "1ProjectRole": 407,
    "1ProjectRole_1": 316,
    "1ProjectStartDate": 411,
    "1ProjectStartDate_1": 320,
    "1ProjectTitle": 405,
    "1ProjectTitle_1": 314,
    "2 Project Client_DataCard1": 162,
    "2 Project Description_DataCard1": 182,
    "2 Project End Date_DataCard1": 177,
    "2 Project Role_DataCard1": 167,
    "2 Project Start Date_DataCard1": 172,
    "2 Project Title_DataCard1": 157,
    "2ProjectClient": 416,
    "2ProjectClient_1": 325,
    "2ProjectDescription": 423,
    "2ProjectDescription_1": 332,
    "2ProjectEndDate": 422,
    "2ProjectEndDate_1": 331,
    "2ProjectRole": 417,
    "2ProjectRole_1": 326,
    "2ProjectStartDate": 421,
    "2ProjectStartDate_1": 330,
    "2ProjectTitle": 415,
    "2ProjectTitle_1": 324,
    "3 Project Client_DataCard1": 192,
    "3 Project Description_DataCard1": 212,
    "3 Project End Date_DataCard1": 207,
    "3 Project Role_DataCard1": 197,
    "3 Project Start Date_DataCard1": 202,
    "3 Project Title_DataCard1": 187,
    "3ProjectClient": 426,
    "3ProjectClient_1": 335,
    "3ProjectDescription": 433,
    "3ProjectDescription_1": 342,
    "3ProjectEndDate": 432,
    "3ProjectEndDate_1": 341,
    "3ProjectRole": 427,
    "3ProjectRole_1": 336,
    "3ProjectStartDate": 431,
    "3ProjectStartDate_1": 340,
    "3ProjectTitle": 425,
    "3ProjectTitle_1": 334,
    "AddSkill": 289,
    "AddSkill_1": 287,
    "AddSkill_2": 304,
    "Alignment_DataCard1": 32,
    "App": 1,
    "Attachments_DataCard1": 217,
    "Background Rectangle": 360,
    "Background Rectangle_1": 378,
    "Background Rectangle_2": 261,
    "Button1": 449,
    "Button1_1": 397,
    "Button1_2": 306,
    "Button1_3": 305,
    "Button1_4": 275,
    "Button1_5": 251,
    "Button1_6": 252,
    "Button1_7": 358,
    "Button2": 365,
    "Button2_1": 371,
    "Button2_2": 369,
    "Button2_3": 366,
    "Button4": 282,
    "Button4_1": 283,
    "Button4_2": 301,
    "Button4_3": 228,
    "Button4_4": 229,
    "Button4_5": 242,
    "Button5_1": 241,
    "Button6": 403,
    "Button6_1": 312,
    "Button7": 447,
    "Button7_1": 445,
    "Button7_2": 446,
    "Button7_3": 448,
    "Button7_4": 354,
    "Button7_5": 355,
    "Button7_6": 356,
    "Button7_7": 357,
    "Checkbox_BPSS": 387,
    "Checkbox_SC": 388,
    "ComboBox2": 222,
    "ComboBoxCourse": 290,
    "ComboBoxQual": 303,
    "ComboBoxSkill": 288,
    "ComboBoxUniversity": 286,
    "Component1": 4,
    "Create": 377,
    "Create CV Button": 373,
    "DataCardKey1": 9,
    "DataCardKey10": 54,
    "DataCardKey11": 59,
    "DataCardKey12": 64,
    "DataCardKey13": 69,
    "DataCardKey14": 74,
    "DataCardKey15": 79,
    "DataCardKey16": 84,
    "DataCardKey17": 89,
    "DataCardKey18": 94,
    "DataCardKey19": 99,
    "DataCardKey2": 14,
    "DataCardKey20": 104,
    "DataCardKey21": 109,
    "DataCardKey22": 114,
    "DataCardKey23": 119,
    "DataCardKey24": 124,
    "DataCardKey25": 129,
    "DataCardKey26": 134,
    "DataCardKey27": 139,
    "DataCardKey28": 144,
    "DataCardKey29": 149,
    "DataCardKey3": 19,
    "DataCardKey30": 154,
    "DataCardKey31": 159,
    "DataCardKey32": 164,
    "DataCardKey33": 169,
    "DataCardKey34": 174,
    "DataCardKey35": 179,
    "DataCardKey36": 184,
    "DataCardKey37": 189,
    "DataCardKey38": 194,
    "DataCardKey39": 199,
    "DataCardKey4": 24,
    "DataCardKey40": 204,
    "DataCardKey41": 209,
    "DataCardKey42": 214,
    "DataCardKey43": 219,
    "DataCardKey5": 29,
    "DataCardKey6": 34,
    "DataCardKey7": 39,
    "DataCardKey8": 44,
    "DataCardKey9": 49,
    "DataCardValue1": 10,
    "DataCardValue10": 55,
    "DataCardValue11": 60,
    "DataCardValue12": 65,
    "DataCardValue13": 70,
    "DataCardValue14": 75,
    "DataCardValue15": 80,
    "DataCardValue16": 85,
    "DataCardValue17": 90,
    "DataCardValue18": 95,
    "DataCardValue19": 100,
    "DataCardValue2": 15,
    "DataCardValue20": 105,
    "DataCardValue21": 110,
    "DataCardValue22": 115,
    "DataCardValue23": 120,
    "DataCardValue24": 125,
    "DataCardValue25": 130,
    "DataCardValue26": 135,
    "DataCardValue27": 140,
    "DataCardValue28": 145,
    "DataCardValue29": 150,
    "DataCardValue3": 20,
    "DataCardValue30": 155,
    "DataCardValue31": 160,
    "DataCardValue32": 165,
    "DataCardValue33": 170,
    "DataCardValue34": 175,
    "DataCardValue35": 180,
    "DataCardValue36": 185,
    "DataCardValue37": 190,
    "DataCardValue38": 195,
    "DataCardValue39": 200,
    "DataCardValue4": 25,
    "DataCardValue40": 205,
    "DataCardValue41": 210,
    "DataCardValue42": 215,
    "DataCardValue43": 220,
    "DataCardValue5": 30,
    "DataCardValue6": 35,
    "DataCardValue7": 40,
    "DataCardValue8": 45,
    "DataCardValue9": 50,
    "DatePicker1_6": 441,
    "DatePicker1_7": 442,
    "DatePicker1_8": 350,
    "DatePicker1_9": 351,
    "Email_1": 392,
    "Email_2": 274,
    "Email_DataCard1": 37,
    "ErrorMessage1": 11,
    "ErrorMessage10": 56,
    "ErrorMessage11": 61,
    "ErrorMessage12": 66,
    "ErrorMessage13": 71,
    "ErrorMessage14": 76,
    "ErrorMessage15": 81,
    "ErrorMessage16": 86,
    "ErrorMessage17": 91,
    "ErrorMessage18": 96,
    "ErrorMessage19": 101,
    "ErrorMessage2": 16,
    "ErrorMessage20": 106,
    "ErrorMessage21": 111,
    "ErrorMessage22": 116,
    "ErrorMessage23": 121,
    "ErrorMessage24": 126,
    "ErrorMessage25": 131,
    "ErrorMessage26": 136,
    "ErrorMessage27": 141,
    "ErrorMessage28": 146,
    "ErrorMessage29": 151,
    "ErrorMessage3": 21,
    "ErrorMessage30": 156,
    "ErrorMessage31": 161,
    "ErrorMessage32": 166,
    "ErrorMessage33": 171,
    "ErrorMessage34": 176,
    "ErrorMessage35": 181,
    "ErrorMessage36": 186,
    "ErrorMessage37": 191,
    "ErrorMessage38": 196,
    "ErrorMessage39": 201,
    "ErrorMessage4": 26,
    "ErrorMessage40": 206,
    "ErrorMessage41": 211,
    "ErrorMessage42": 216,
    "ErrorMessage43": 221,
    "ErrorMessage5": 31,
    "ErrorMessage6": 36,
    "ErrorMessage7": 41,
    "ErrorMessage8": 46,
    "ErrorMessage9": 51,
    "Experience1": 404,
    "Experience1_1": 313,
    "Experience2": 414,
    "Experience2_1": 323,
    "Experience3": 424,
    "Experience3_1": 333,
    "Experience4": 434,
    "Experience4_1": 343,
    "First Name_DataCard1": 17,
    "Form1": 6,
    "Gallery1": 291,
    "Gallery2": 296,
    "galleryTemplate1": 292,
    "galleryTemplate2": 297,
    "Group1_1": 253,
    "Group2_1": 254,
    "Group3_1": 255,
    "Group4_1": 256,
    "Group5_1": 257,
    "Group6_1": 258,
    "Host": 3,
    "Icon1": 278,
    "Icon1_1": 225,
    "Icon2": 367,
    "Icon2_1": 372,
    "Icon2_2": 370,
    "Icon2_3": 368,
    "Icon3": 293,
    "Icon4": 381,
    "Icon4_1": 266,
    "Icon5": 295,
    "Icon6": 298,
    "Icon7": 300,
    "Icon8": 400,
    "Icon8_1": 309,
    "Image1": 361,
    "Image1_2": 380,
    "Image1_3": 263,
    "Image2": 363,
    "Image2_1": 383,
    "Image2_2": 265,
    "Image3": 362,
    "Image3_1": 382,
    "Image3_2": 264,
    "Image4": 280,
    "Image4_1": 401,
    "Image4_2": 226,
    "Image4_3": 310,
    "Interests": 395,
    "Interests_DataCard1": 122,
    "Label1": 393,
    "Label1_2": 396,
    "Label12": 409,
    "Label12_1": 410,
    "Label12_10": 328,
    "Label12_11": 329,
    "Label12_12": 338,
    "Label12_13": 339,
    "Label12_14": 348,
    "Label12_15": 349,
    "Label12_2": 419,
    "Label12_3": 420,
    "Label12_4": 429,
    "Label12_5": 430,
    "Label12_6": 439,
    "Label12_7": 440,
    "Label12_8": 318,
    "Label12_9": 319,
    "Label13": 444,
    "Label13_1": 353,
    "Label2": 294,
    "Label2_2": 273,
    "Label4": 364,
    "Label4_1": 379,
    "Label4_2": 262,
    "Label5": 299,
    "Label5_1": 389,
    "Label5_10": 230,
    "Label5_11": 231,
    "Label5_12": 243,
    "Label5_13": 317,
    "Label5_14": 327,
    "Label5_15": 337,
    "Label5_16": 347,
    "Label5_17": 302,
    "Label5_2": 408,
    "Label5_3": 418,
    "Label5_4": 284,
    "Label5_5": 285,
    "Label5_6": 394,
    "Label5_7": 428,
    "Label5_8": 438,
    "Label5_9": 269,
    "Label6": 281,
    "Label6_1": 402,
    "Label6_2": 227,
    "Label6_3": 311,
    "Last Name_DataCard1": 22,
    "Microsoft Profile": 279,
    "Microsoft Profile_DataCard1": 12,
    "Name_1": 391,
    "Name_2": 272,
    "Primary Alignment": 384,
    "Primary Alignment_1": 268,
    "Profesional Experience": 398,
    "Profile box": 390,
    "Profile box_1": 271,
    "Profile_DataCard1": 42,
    "ProfilePic_2": 386,
    "ProfilePic_3": 270,
    "Qualification 1_DataCard1": 107,
    "Qualification 2_DataCard1": 112,
    "Qualification 3_DataCard1": 117,
    "Rectangle2": 277,
    "Rectangle2_1": 399,
    "Rectangle2_2": 224,
    "Rectangle2_3": 308,
    "Role Title_DataCard1": 27,
    "RoleTitle": 385,
    "RoleTitle_1": 267,
    "Screen1": 5,
    "Search CV Button": 375,
    "Skill 1 Evidence _DataCard1": 52,
    "Skill 1_DataCard1": 47,
    "Skill 2 Evidence_DataCard1": 62,
    "Skill 2_DataCard1": 57,
    "Skill 3 Evidence_DataCard1": 72,
    "Skill 3_DataCard1": 67,
    "Skill 4 Evidence_DataCard1": 97,
    "Skill 4_DataCard1": 77,
    "Skill 5 Evidence_DataCard1": 92,
    "Skill 5_DataCard1": 82,
    "Skill 6 Evidence_DataCard1": 102,
    "Skill 6_DataCard1": 87,
    "Skills Competancies & Qualifications": 276,
    "StarVisible1": 8,
    "StarVisible10": 53,
    "StarVisible11": 58,
    "StarVisible12": 63,
    "StarVisible13": 68,
    "StarVisible14": 73,
    "StarVisible15": 78,
    "StarVisible16": 83,
    "StarVisible17": 88,
    "StarVisible18": 93,
    "StarVisible19": 98,
    "StarVisible2": 13,
    "StarVisible20": 103,
    "StarVisible21": 108,
    "StarVisible22": 113,
    "StarVisible23": 118,
    "StarVisible24": 123,
    "StarVisible25": 128,
    "StarVisible26": 133,
    "StarVisible27": 138,
    "StarVisible28": 143,
    "StarVisible29": 148,
    "StarVisible3": 18,
    "StarVisible30": 153,
    "StarVisible31": 158,
    "StarVisible32": 163,
    "StarVisible33": 168,
    "StarVisible34": 173,
    "StarVisible35": 178,
    "StarVisible36": 183,
    "StarVisible37": 188,
    "StarVisible38": 193,
    "StarVisible39": 198,
    "StarVisible4": 23,
    "StarVisible40": 203,
    "StarVisible41": 208,
    "StarVisible42": 213,
    "StarVisible43": 218,
    "StarVisible5": 28,
    "StarVisible6": 33,
    "StarVisible7": 38,
    "StarVisible8": 43,
    "StarVisible9": 48,
    "SuccessScreen": 259,
    "TextInput2_10": 247,
    "TextInput2_11": 249,
    "TextInput2_6": 233,
    "TextInput2_7": 236,
    "TextInput2_8": 239,
    "TextInput2_9": 244,
    "TextInput3_10": 248,
    "TextInput3_11": 250,
    "TextInput3_6": 234,
    "TextInput3_7": 237,
    "TextInput3_8": 240,
    "TextInput3_9": 245,
    "TextInput4_3": 232,
    "TextInput4_4": 235,
    "TextInput4_5": 238,
    "TextInput6_1": 246,
    "TextInput7_3": 443,
    "TextInput7_4": 352,
    "TextInput8_10": 436,
    "TextInput8_11": 437,
    "TextInput8_12": 344,
    "TextInput8_13": 345,
    "TextInput8_14": 346,
    "TextInput8_9": 435,
    "Title_DataCard1": 7,
    "Update": 260,
    "Update CV Button": 374,
    "Update_Profesional Experience": 307,
    "Update_Skills Competancies & Qualifications": 223,
    "View CV Button": 376,
    "Welcome": 359
  },
  "FunctionParamsInvariantScripts": {},
  "FunctionParamsInvariantScriptsOnInstances": {},
  "HeaderLastSavedDateTimeUTC": "03/12/2024 16:51:52",
  "IsLegacyComponentAllowGlobalScopeCase": false,
  "LocalConnectionIDReferences": {
    "0fa35610-3dad-4a9b-9e62-152ac7a52071": "\"/providers/microsoft.powerapps/apis/shared_office365users/connections/3744c0035e4e483b9d7e1accfcb8a55c\"",
    "6dfc64e3-2225-432e-945b-fa7298f7ceec": "\"/providers/microsoft.powerapps/apis/shared_office365/connections/585e0ab35b1d47e188651505907d4eb9\"",
    "f820e0ef-89ca-4bff-93dc-c2e95c68d321": "\"/providers/microsoft.powerapps/apis/shared_sharepointonline/connections/4d712f27490849f8bc56179e2af4db70\""
  },
  "LocalDatabaseReferencesAsEmpty": true,
  "LocalResourceFileNames": {
    "Cap squiggle": "0001.png",
    "Logo Blue": "0002.png",
    "Picture5": "0003.png",
    "Screenshot 2024-03-04 120003": "0004.png",
    "White Logo Capgemini Invent": "0005.png"
  },
  "LocalResourceRootPaths": {
    "Cap squiggle": "https://docserverpwaprodneu.blob.core.windows.net/4980caed-24a4-442f-a063-1ec340592025-1/resource/Assets0Images00001.png?skoid=58690ece-ec83-4ce2-9ce8-883d4d6a54ee&sktid=975f013f-7f24-47e8-a7d3-abc4752bf346&skt=2024-03-12T16%3A17%3A52Z&ske=2024-03-13T16%3A32%3A52Z&sks=b&skv=2022-11-02&sv=2022-11-02&spr=https&se=2024-03-13T16%3A32%3A52Z&sr=b&sp=r&sig=1wjeq44Kb8iQuZiQMXECs0mWJqez%2FOEwx%2B8QIUE5uDg%3D",
    "Logo Blue": "https://docserverpwaprodneu.blob.core.windows.net/4980caed-24a4-442f-a063-1ec340592025-1/resource/Assets0Images00002.png?skoid=58690ece-ec83-4ce2-9ce8-883d4d6a54ee&sktid=975f013f-7f24-47e8-a7d3-abc4752bf346&skt=2024-03-12T16%3A17%3A52Z&ske=2024-03-13T16%3A32%3A52Z&sks=b&skv=2022-11-02&sv=2022-11-02&spr=https&se=2024-03-13T16%3A32%3A52Z&sr=b&sp=r&sig=5qaI3CnValLLLNx7aNsd9uHQdQ32dEQW8nrVDXTt1N8%3D",
    "Picture5": "https://docserverpwaprodneu.blob.core.windows.net/4980caed-24a4-442f-a063-1ec340592025-1/resource/Assets0Images00003.png?skoid=58690ece-ec83-4ce2-9ce8-883d4d6a54ee&sktid=975f013f-7f24-47e8-a7d3-abc4752bf346&skt=2024-03-12T16%3A17%3A52Z&ske=2024-03-13T16%3A32%3A52Z&sks=b&skv=2022-11-02&sv=2022-11-02&spr=https&se=2024-03-13T16%3A32%3A52Z&sr=b&sp=r&sig=gT5%2Be6BUd%2BRyoYIDZsdTprfAlNIfb0ryIjJ1NVI0RAk%3D",
    "Screenshot 2024-03-04 120003": "https://docserverpwaprodneu.blob.core.windows.net/4980caed-24a4-442f-a063-1ec340592025-1/resource/Assets0Images00004.png?skoid=58690ece-ec83-4ce2-9ce8-883d4d6a54ee&sktid=975f013f-7f24-47e8-a7d3-abc4752bf346&skt=2024-03-12T16%3A17%3A52Z&ske=2024-03-13T16%3A32%3A52Z&sks=b&skv=2022-11-02&sv=2022-11-02&spr=https&se=2024-03-13T16%3A32%3A52Z&sr=b&sp=r&sig=7f3PUVV7UB%2BcT2ypNtrSh9%2BPfFSMItJABRW4PcvDVMM%3D",
    "White Logo Capgemini Invent": "https://docserverpwaprodneu.blob.core.windows.net/4980caed-24a4-442f-a063-1ec340592025-1/resource/Assets0Images00005.png?skoid=58690ece-ec83-4ce2-9ce8-883d4d6a54ee&sktid=975f013f-7f24-47e8-a7d3-abc4752bf346&skt=2024-03-12T16%3A17%3A52Z&ske=2024-03-13T16%3A32%3A52Z&sks=b&skv=2022-11-02&sv=2022-11-02&spr=https&se=2024-03-13T16%3A32%3A52Z&sr=b&sp=r&sig=tlxgUzEFnzLqiVRtEkX0QQeGHkl8ULiMg9hc74hMVmk%3D"
  },
  "OrderComponentMetadata": {
    "6b01bf047f29498a89aa71ff084a0b2f": 0
  },
  "OrderComponentTemplate": {
    "6b01bf047f29498a89aa71ff084a0b2f": 0
  },
  "OrderDataSource": {
    "ComboBoxSample": 2,
    "CustomGallerySample": 3,
    "CV Generator": 4,
    "DropDownSample": 5,
    "Education": 6,
    "Office365Outlook": 0,
    "Office365Users": 1,
    "Qualifications": 8,
    "SkillsCollection": 7
  },
  "OrderGroupControls": {
    "Create CV Button": {
      "Button2": 0,
      "Icon2": 1
    },
    "Group1_1": {
      "TextInput2_6": 0,
      "TextInput3_6": 1
    },
    "Group2_1": {
      "TextInput2_7": 0,
      "TextInput3_7": 1
    },
    "Group3_1": {
      "TextInput2_8": 0,
      "TextInput3_8": 1
    },
    "Group4_1": {
      "TextInput2_9": 0,
      "TextInput3_9": 1
    },
    "Group5_1": {
      "TextInput2_10": 0,
      "TextInput3_10": 1
    },
    "Group6_1": {
      "TextInput2_11": 0,
      "TextInput3_11": 1
    },
    "Search CV Button": {
      "Button2_2": 0,
      "Icon2_2": 1
    },
    "Update CV Button": {
      "Button2_3": 0,
      "Icon2_3": 1
    },
    "View CV Button": {
      "Button2_1": 0,
      "Icon2_1": 1
    }
  },
  "OrderPcfTemplate": {},
  "OrderTemplate": {},
  "OrderXMLTemplate": {
    "attachments": 5,
    "button": 9,
    "checkbox": 13,
    "combobox": 3,
    "datepicker": 4,
    "dropdown": 10,
    "form": 0,
    "gallery": 11,
    "groupContainer": 12,
    "icon": 7,
    "image": 8,
    "label": 1,
    "rectangle": 6,
    "text": 2
  },
  "OverridablePropertiesEntry": {
    "1 Project Client_DataCard1": {},
    "1 Project Description_DataCard1": {},
    "1 Project End Date_DataCard1": {},
    "1 Project Role_DataCard1": {},
    "1 Project Start Date_DataCard1": {},
    "1 Project Title_DataCard1": {},
    "1ProjectClient": {},
    "1ProjectClient_1": {},
    "1ProjectDescription": {},
    "1ProjectDescription_1": {},
    "1ProjectEndDate": {},
    "1ProjectEndDate_1": {},
    "1ProjectRole": {},
    "1ProjectRole_1": {},
    "1ProjectStartDate": {},
    "1ProjectStartDate_1": {},
    "1ProjectTitle": {},
    "1ProjectTitle_1": {},
    "2 Project Client_DataCard1": {},
    "2 Project Description_DataCard1": {},
    "2 Project End Date_DataCard1": {},
    "2 Project Role_DataCard1": {},
    "2 Project Start Date_DataCard1": {},
    "2 Project Title_DataCard1": {},
    "2ProjectClient": {},
    "2ProjectClient_1": {},
    "2ProjectDescription": {},
    "2ProjectDescription_1": {},
    "2ProjectEndDate": {},
    "2ProjectEndDate_1": {},
    "2ProjectRole": {},
    "2ProjectRole_1": {},
    "2ProjectStartDate": {},
    "2ProjectStartDate_1": {},
    "2ProjectTitle": {},
    "2ProjectTitle_1": {},
    "3 Project Client_DataCard1": {},
    "3 Project Description_DataCard1": {},
    "3 Project End Date_DataCard1": {},
    "3 Project Role_DataCard1": {},
    "3 Project Start Date_DataCard1": {},
    "3 Project Title_DataCard1": {},
    "3ProjectClient": {},
    "3ProjectClient_1": {},
    "3ProjectDescription": {},
    "3ProjectDescription_1": {},
    "3ProjectEndDate": {},
    "3ProjectEndDate_1": {},
    "3ProjectRole": {},
    "3ProjectRole_1": {},
    "3ProjectStartDate": {},
    "3ProjectStartDate_1": {},
    "3ProjectTitle": {},
    "3ProjectTitle_1": {},
    "AddSkill": {},
    "AddSkill_1": {},
    "AddSkill_2": {},
    "Alignment_DataCard1": {},
    "App": {},
    "Attachments_DataCard1": {},
    "Background Rectangle": {},
    "Background Rectangle_1": {},
    "Background Rectangle_2": {},
    "Button1": {},
    "Button1_1": {},
    "Button1_2": {},
    "Button1_3": {},
    "Button1_4": {},
    "Button1_5": {},
    "Button1_6": {},
    "Button1_7": {},
    "Button2": {},
    "Button2_1": {},
    "Button2_2": {},
    "Button2_3": {},
    "Button4": {},
    "Button4_1": {},
    "Button4_2": {},
    "Button4_3": {},
    "Button4_4": {},
    "Button4_5": {},
    "Button5_1": {},
    "Button6": {},
    "Button6_1": {},
    "Button7": {},
    "Button7_1": {},
    "Button7_2": {},
    "Button7_3": {},
    "Button7_4": {},
    "Button7_5": {},
    "Button7_6": {},
    "Button7_7": {},
    "Checkbox_BPSS": {},
    "Checkbox_SC": {},
    "ComboBox2": {},
    "ComboBoxCourse": {},
    "ComboBoxQual": {},
    "ComboBoxSkill": {},
    "ComboBoxUniversity": {},
    "Component1": {},
    "Create": {},
    "Create CV Button": {},
    "DataCardKey1": {},
    "DataCardKey10": {},
    "DataCardKey11": {},
    "DataCardKey12": {},
    "DataCardKey13": {},
    "DataCardKey14": {},
    "DataCardKey15": {},
    "DataCardKey16": {},
    "DataCardKey17": {},
    "DataCardKey18": {},
    "DataCardKey19": {},
    "DataCardKey2": {},
    "DataCardKey20": {},
    "DataCardKey21": {},
    "DataCardKey22": {},
    "DataCardKey23": {},
    "DataCardKey24": {},
    "DataCardKey25": {},
    "DataCardKey26": {},
    "DataCardKey27": {},
    "DataCardKey28": {},
    "DataCardKey29": {},
    "DataCardKey3": {},
    "DataCardKey30": {},
    "DataCardKey31": {},
    "DataCardKey32": {},
    "DataCardKey33": {},
    "DataCardKey34": {},
    "DataCardKey35": {},
    "DataCardKey36": {},
    "DataCardKey37": {},
    "DataCardKey38": {},
    "DataCardKey39": {},
    "DataCardKey4": {},
    "DataCardKey40": {},
    "DataCardKey41": {},
    "DataCardKey42": {},
    "DataCardKey43": {},
    "DataCardKey5": {},
    "DataCardKey6": {},
    "DataCardKey7": {},
    "DataCardKey8": {},
    "DataCardKey9": {},
    "DataCardValue1": {},
    "DataCardValue10": {},
    "DataCardValue11": {},
    "DataCardValue12": {},
    "DataCardValue13": {},
    "DataCardValue14": {},
    "DataCardValue15": {},
    "DataCardValue16": {},
    "DataCardValue17": {},
    "DataCardValue18": {},
    "DataCardValue19": {},
    "DataCardValue2": {},
    "DataCardValue20": {},
    "DataCardValue21": {},
    "DataCardValue22": {},
    "DataCardValue23": {},
    "DataCardValue24": {},
    "DataCardValue25": {},
    "DataCardValue26": {},
    "DataCardValue27": {},
    "DataCardValue28": {},
    "DataCardValue29": {},
    "DataCardValue3": {},
    "DataCardValue30": {},
    "DataCardValue31": {},
    "DataCardValue32": {},
    "DataCardValue33": {},
    "DataCardValue34": {},
    "DataCardValue35": {},
    "DataCardValue36": {},
    "DataCardValue37": {},
    "DataCardValue38": {},
    "DataCardValue39": {},
    "DataCardValue4": {},
    "DataCardValue40": {},
    "DataCardValue41": {},
    "DataCardValue42": {},
    "DataCardValue43": {},
    "DataCardValue5": {},
    "DataCardValue6": {},
    "DataCardValue7": {},
    "DataCardValue8": {},
    "DataCardValue9": {},
    "DatePicker1_6": {},
    "DatePicker1_7": {},
    "DatePicker1_8": {},
    "DatePicker1_9": {},
    "Email_1": {},
    "Email_2": {},
    "Email_DataCard1": {},
    "ErrorMessage1": {},
    "ErrorMessage10": {},
    "ErrorMessage11": {},
    "ErrorMessage12": {},
    "ErrorMessage13": {},
    "ErrorMessage14": {},
    "ErrorMessage15": {},
    "ErrorMessage16": {},
    "ErrorMessage17": {},
    "ErrorMessage18": {},
    "ErrorMessage19": {},
    "ErrorMessage2": {},
    "ErrorMessage20": {},
    "ErrorMessage21": {},
    "ErrorMessage22": {},
    "ErrorMessage23": {},
    "ErrorMessage24": {},
    "ErrorMessage25": {},
    "ErrorMessage26": {},
    "ErrorMessage27": {},
    "ErrorMessage28": {},
    "ErrorMessage29": {},
    "ErrorMessage3": {},
    "ErrorMessage30": {},
    "ErrorMessage31": {},
    "ErrorMessage32": {},
    "ErrorMessage33": {},
    "ErrorMessage34": {},
    "ErrorMessage35": {},
    "ErrorMessage36": {},
    "ErrorMessage37": {},
    "ErrorMessage38": {},
    "ErrorMessage39": {},
    "ErrorMessage4": {},
    "ErrorMessage40": {},
    "ErrorMessage41": {},
    "ErrorMessage42": {},
    "ErrorMessage43": {},
    "ErrorMessage5": {},
    "ErrorMessage6": {},
    "ErrorMessage7": {},
    "ErrorMessage8": {},
    "ErrorMessage9": {},
    "Experience1": {},
    "Experience1_1": {},
    "Experience2": {},
    "Experience2_1": {},
    "Experience3": {},
    "Experience3_1": {},
    "Experience4": {},
    "Experience4_1": {},
    "First Name_DataCard1": {},
    "Form1": {},
    "Gallery1": {},
    "Gallery2": {},
    "galleryTemplate1": {},
    "galleryTemplate2": {},
    "Group1_1": {},
    "Group2_1": {},
    "Group3_1": {},
    "Group4_1": {},
    "Group5_1": {},
    "Group6_1": {},
    "Host": {},
    "Icon1": {},
    "Icon1_1": {},
    "Icon2": {},
    "Icon2_1": {},
    "Icon2_2": {},
    "Icon2_3": {},
    "Icon3": {},
    "Icon4": {},
    "Icon4_1": {},
    "Icon5": {},
    "Icon6": {},
    "Icon7": {},
    "Icon8": {},
    "Icon8_1": {},
    "Image1": {},
    "Image1_2": {},
    "Image1_3": {},
    "Image2": {},
    "Image2_1": {},
    "Image2_2": {},
    "Image3": {},
    "Image3_1": {},
    "Image3_2": {},
    "Image4": {},
    "Image4_1": {},
    "Image4_2": {},
    "Image4_3": {},
    "Interests": {},
    "Interests_DataCard1": {},
    "Label1": {},
    "Label1_2": {},
    "Label12": {},
    "Label12_1": {},
    "Label12_10": {},
    "Label12_11": {},
    "Label12_12": {},
    "Label12_13": {},
    "Label12_14": {},
    "Label12_15": {},
    "Label12_2": {},
    "Label12_3": {},
    "Label12_4": {},
    "Label12_5": {},
    "Label12_6": {},
    "Label12_7": {},
    "Label12_8": {},
    "Label12_9": {},
    "Label13": {},
    "Label13_1": {},
    "Label2": {},
    "Label2_2": {},
    "Label4": {},
    "Label4_1": {},
    "Label4_2": {},
    "Label5": {},
    "Label5_1": {},
    "Label5_10": {},
    "Label5_11": {},
    "Label5_12": {},
    "Label5_13": {},
    "Label5_14": {},
    "Label5_15": {},
    "Label5_16": {},
    "Label5_17": {},
    "Label5_2": {},
    "Label5_3": {},
    "Label5_4": {},
    "Label5_5": {},
    "Label5_6": {},
    "Label5_7": {},
    "Label5_8": {},
    "Label5_9": {},
    "Label6": {},
    "Label6_1": {},
    "Label6_2": {},
    "Label6_3": {},
    "Last Name_DataCard1": {},
    "Microsoft Profile": {},
    "Microsoft Profile_DataCard1": {},
    "Name_1": {},
    "Name_2": {},
    "Primary Alignment": {},
    "Primary Alignment_1": {},
    "Profesional Experience": {},
    "Profile box": {},
    "Profile box_1": {},
    "Profile_DataCard1": {},
    "ProfilePic_2": {},
    "ProfilePic_3": {},
    "Qualification 1_DataCard1": {},
    "Qualification 2_DataCard1": {},
    "Qualification 3_DataCard1": {},
    "Rectangle2": {},
    "Rectangle2_1": {},
    "Rectangle2_2": {},
    "Rectangle2_3": {},
    "Role Title_DataCard1": {},
    "RoleTitle": {},
    "RoleTitle_1": {},
    "Screen1": {},
    "Search CV Button": {},
    "Skill 1 Evidence _DataCard1": {},
    "Skill 1_DataCard1": {},
    "Skill 2 Evidence_DataCard1": {},
    "Skill 2_DataCard1": {},
    "Skill 3 Evidence_DataCard1": {},
    "Skill 3_DataCard1": {},
    "Skill 4 Evidence_DataCard1": {},
    "Skill 4_DataCard1": {},
    "Skill 5 Evidence_DataCard1": {},
    "Skill 5_DataCard1": {},
    "Skill 6 Evidence_DataCard1": {},
    "Skill 6_DataCard1": {},
    "Skills Competancies & Qualifications": {},
    "StarVisible1": {},
    "StarVisible10": {},
    "StarVisible11": {},
    "StarVisible12": {},
    "StarVisible13": {},
    "StarVisible14": {},
    "StarVisible15": {},
    "StarVisible16": {},
    "StarVisible17": {},
    "StarVisible18": {},
    "StarVisible19": {},
    "StarVisible2": {},
    "StarVisible20": {},
    "StarVisible21": {},
    "StarVisible22": {},
    "StarVisible23": {},
    "StarVisible24": {},
    "StarVisible25": {},
    "StarVisible26": {},
    "StarVisible27": {},
    "StarVisible28": {},
    "StarVisible29": {},
    "StarVisible3": {},
    "StarVisible30": {},
    "StarVisible31": {},
    "StarVisible32": {},
    "StarVisible33": {},
    "StarVisible34": {},
    "StarVisible35": {},
    "StarVisible36": {},
    "StarVisible37": {},
    "StarVisible38": {},
    "StarVisible39": {},
    "StarVisible4": {},
    "StarVisible40": {},
    "StarVisible41": {},
    "StarVisible42": {},
    "StarVisible43": {},
    "StarVisible5": {},
    "StarVisible6": {},
    "StarVisible7": {},
    "StarVisible8": {},
    "StarVisible9": {},
    "SuccessScreen": {},
    "TextInput2_10": {},
    "TextInput2_11": {},
    "TextInput2_6": {},
    "TextInput2_7": {},
    "TextInput2_8": {},
    "TextInput2_9": {},
    "TextInput3_10": {},
    "TextInput3_11": {},
    "TextInput3_6": {},
    "TextInput3_7": {},
    "TextInput3_8": {},
    "TextInput3_9": {},
    "TextInput4_3": {},
    "TextInput4_4": {},
    "TextInput4_5": {},
    "TextInput6_1": {},
    "TextInput7_3": {},
    "TextInput7_4": {},
    "TextInput8_10": {},
    "TextInput8_11": {},
    "TextInput8_12": {},
    "TextInput8_13": {},
    "TextInput8_14": {},
    "TextInput8_9": {},
    "Title_DataCard1": {},
    "Update": {},
    "Update CV Button": {},
    "Update_Profesional Experience": {},
    "Update_Skills Competancies & Qualifications": {},
    "View CV Button": {},
    "Welcome": {}
  },
  "PCFDynamicSchemaForIRRetrievalEntry": {},
  "PCFTemplateEntry": {},
  "PublishOrderIndices": {
    "1 Project Client_DataCard1": 345,
    "1 Project Description_DataCard1": 365,
    "1 Project End Date_DataCard1": 360,
    "1 Project Role_DataCard1": 350,
    "1 Project Start Date_DataCard1": 355,
    "1 Project Title_DataCard1": 340,
    "1ProjectClient": 74,
    "1ProjectClient_1": 175,
    "1ProjectDescription": 81,
    "1ProjectDescription_1": 182,
    "1ProjectEndDate": 80,
    "1ProjectEndDate_1": 181,
    "1ProjectRole": 75,
    "1ProjectRole_1": 176,
    "1ProjectStartDate": 79,
    "1ProjectStartDate_1": 180,
    "1ProjectTitle": 73,
    "1ProjectTitle_1": 174,
    "2 Project Client_DataCard1": 375,
    "2 Project Description_DataCard1": 395,
    "2 Project End Date_DataCard1": 390,
    "2 Project Role_DataCard1": 380,
    "2 Project Start Date_DataCard1": 385,
    "2 Project Title_DataCard1": 370,
    "2ProjectClient": 84,
    "2ProjectClient_1": 185,
    "2ProjectDescription": 91,
    "2ProjectDescription_1": 192,
    "2ProjectEndDate": 90,
    "2ProjectEndDate_1": 191,
    "2ProjectRole": 85,
    "2ProjectRole_1": 186,
    "2ProjectStartDate": 89,
    "2ProjectStartDate_1": 190,
    "2ProjectTitle": 83,
    "2ProjectTitle_1": 184,
    "3 Project Client_DataCard1": 405,
    "3 Project Description_DataCard1": 425,
    "3 Project End Date_DataCard1": 420,
    "3 Project Role_DataCard1": 410,
    "3 Project Start Date_DataCard1": 415,
    "3 Project Title_DataCard1": 400,
    "3ProjectClient": 94,
    "3ProjectClient_1": 195,
    "3ProjectDescription": 101,
    "3ProjectDescription_1": 202,
    "3ProjectEndDate": 100,
    "3ProjectEndDate_1": 201,
    "3ProjectRole": 95,
    "3ProjectRole_1": 196,
    "3ProjectStartDate": 99,
    "3ProjectStartDate_1": 200,
    "3ProjectTitle": 93,
    "3ProjectTitle_1": 194,
    "AddSkill": 49,
    "AddSkill_1": 47,
    "AddSkill_2": 64,
    "Alignment_DataCard1": 245,
    "App": 0,
    "Attachments_DataCard1": 430,
    "Background Rectangle": 0,
    "Background Rectangle_1": 17,
    "Background Rectangle_2": 118,
    "Button1": 117,
    "Button1_1": 36,
    "Button1_2": 66,
    "Button1_3": 65,
    "Button1_4": 132,
    "Button1_5": 166,
    "Button1_6": 167,
    "Button1_7": 218,
    "Button2": 7,
    "Button2_1": 15,
    "Button2_2": 12,
    "Button2_3": 8,
    "Button4": 42,
    "Button4_1": 43,
    "Button4_2": 61,
    "Button4_3": 143,
    "Button4_4": 144,
    "Button4_5": 157,
    "Button5_1": 156,
    "Button6": 71,
    "Button6_1": 172,
    "Button7": 115,
    "Button7_1": 113,
    "Button7_2": 114,
    "Button7_3": 116,
    "Button7_4": 214,
    "Button7_5": 215,
    "Button7_6": 216,
    "Button7_7": 217,
    "Checkbox_BPSS": 26,
    "Checkbox_SC": 27,
    "ComboBox2": 435,
    "ComboBoxCourse": 50,
    "ComboBoxQual": 63,
    "ComboBoxSkill": 48,
    "ComboBoxUniversity": 46,
    "Component1": 1,
    "Create": 4,
    "Create CV Button": 5,
    "DataCardKey1": 222,
    "DataCardKey10": 267,
    "DataCardKey11": 272,
    "DataCardKey12": 277,
    "DataCardKey13": 282,
    "DataCardKey14": 287,
    "DataCardKey15": 292,
    "DataCardKey16": 297,
    "DataCardKey17": 302,
    "DataCardKey18": 307,
    "DataCardKey19": 312,
    "DataCardKey2": 227,
    "DataCardKey20": 317,
    "DataCardKey21": 322,
    "DataCardKey22": 327,
    "DataCardKey23": 332,
    "DataCardKey24": 337,
    "DataCardKey25": 342,
    "DataCardKey26": 347,
    "DataCardKey27": 352,
    "DataCardKey28": 357,
    "DataCardKey29": 362,
    "DataCardKey3": 232,
    "DataCardKey30": 367,
    "DataCardKey31": 372,
    "DataCardKey32": 377,
    "DataCardKey33": 382,
    "DataCardKey34": 387,
    "DataCardKey35": 392,
    "DataCardKey36": 397,
    "DataCardKey37": 402,
    "DataCardKey38": 407,
    "DataCardKey39": 412,
    "DataCardKey4": 237,
    "DataCardKey40": 417,
    "DataCardKey41": 422,
    "DataCardKey42": 427,
    "DataCardKey43": 432,
    "DataCardKey5": 242,
    "DataCardKey6": 247,
    "DataCardKey7": 252,
    "DataCardKey8": 257,
    "DataCardKey9": 262,
    "DataCardValue1": 223,
    "DataCardValue10": 268,
    "DataCardValue11": 273,
    "DataCardValue12": 278,
    "DataCardValue13": 283,
    "DataCardValue14": 288,
    "DataCardValue15": 293,
    "DataCardValue16": 298,
    "DataCardValue17": 303,
    "DataCardValue18": 308,
    "DataCardValue19": 313,
    "DataCardValue2": 228,
    "DataCardValue20": 318,
    "DataCardValue21": 323,
    "DataCardValue22": 328,
    "DataCardValue23": 333,
    "DataCardValue24": 338,
    "DataCardValue25": 343,
    "DataCardValue26": 348,
    "DataCardValue27": 353,
    "DataCardValue28": 358,
    "DataCardValue29": 363,
    "DataCardValue3": 233,
    "DataCardValue30": 368,
    "DataCardValue31": 373,
    "DataCardValue32": 378,
    "DataCardValue33": 383,
    "DataCardValue34": 388,
    "DataCardValue35": 393,
    "DataCardValue36": 398,
    "DataCardValue37": 403,
    "DataCardValue38": 408,
    "DataCardValue39": 413,
    "DataCardValue4": 238,
    "DataCardValue40": 418,
    "DataCardValue41": 423,
    "DataCardValue42": 428,
    "DataCardValue43": 433,
    "DataCardValue5": 243,
    "DataCardValue6": 248,
    "DataCardValue7": 253,
    "DataCardValue8": 258,
    "DataCardValue9": 263,
    "DatePicker1_6": 109,
    "DatePicker1_7": 110,
    "DatePicker1_8": 210,
    "DatePicker1_9": 211,
    "Email_1": 31,
    "Email_2": 131,
    "Email_DataCard1": 250,
    "ErrorMessage1": 224,
    "ErrorMessage10": 269,
    "ErrorMessage11": 274,
    "ErrorMessage12": 279,
    "ErrorMessage13": 284,
    "ErrorMessage14": 289,
    "ErrorMessage15": 294,
    "ErrorMessage16": 299,
    "ErrorMessage17": 304,
    "ErrorMessage18": 309,
    "ErrorMessage19": 314,
    "ErrorMessage2": 229,
    "ErrorMessage20": 319,
    "ErrorMessage21": 324,
    "ErrorMessage22": 329,
    "ErrorMessage23": 334,
    "ErrorMessage24": 339,
    "ErrorMessage25": 344,
    "ErrorMessage26": 349,
    "ErrorMessage27": 354,
    "ErrorMessage28": 359,
    "ErrorMessage29": 364,
    "ErrorMessage3": 234,
    "ErrorMessage30": 369,
    "ErrorMessage31": 374,
    "ErrorMessage32": 379,
    "ErrorMessage33": 384,
    "ErrorMessage34": 389,
    "ErrorMessage35": 394,
    "ErrorMessage36": 399,
    "ErrorMessage37": 404,
    "ErrorMessage38": 409,
    "ErrorMessage39": 414,
    "ErrorMessage4": 239,
    "ErrorMessage40": 419,
    "ErrorMessage41": 424,
    "ErrorMessage42": 429,
    "ErrorMessage43": 434,
    "ErrorMessage5": 244,
    "ErrorMessage6": 249,
    "ErrorMessage7": 254,
    "ErrorMessage8": 259,
    "ErrorMessage9": 264,
    "Experience1": 72,
    "Experience1_1": 173,
    "Experience2": 82,
    "Experience2_1": 183,
    "Experience3": 92,
    "Experience3_1": 193,
    "Experience4": 102,
    "Experience4_1": 203,
    "First Name_DataCard1": 230,
    "Form1": 219,
    "Gallery1": 51,
    "Gallery2": 56,
    "galleryTemplate1": 52,
    "galleryTemplate2": 57,
    "Group1_1": 137,
    "Group2_1": 138,
    "Group3_1": 139,
    "Group4_1": 140,
    "Group5_1": 141,
    "Group6_1": 142,
    "Host": 0,
    "Icon1": 38,
    "Icon1_1": 134,
    "Icon2": 9,
    "Icon2_1": 16,
    "Icon2_2": 13,
    "Icon2_3": 10,
    "Icon3": 53,
    "Icon4": 20,
    "Icon4_1": 123,
    "Icon5": 55,
    "Icon6": 58,
    "Icon7": 60,
    "Icon8": 68,
    "Icon8_1": 169,
    "Image1": 1,
    "Image1_2": 19,
    "Image1_3": 120,
    "Image2": 3,
    "Image2_1": 22,
    "Image2_2": 122,
    "Image3": 2,
    "Image3_1": 21,
    "Image3_2": 121,
    "Image4": 40,
    "Image4_1": 69,
    "Image4_2": 135,
    "Image4_3": 170,
    "Interests": 34,
    "Interests_DataCard1": 335,
    "Label1": 32,
    "Label1_2": 35,
    "Label12": 77,
    "Label12_1": 78,
    "Label12_10": 188,
    "Label12_11": 189,
    "Label12_12": 198,
    "Label12_13": 199,
    "Label12_14": 208,
    "Label12_15": 209,
    "Label12_2": 87,
    "Label12_3": 88,
    "Label12_4": 97,
    "Label12_5": 98,
    "Label12_6": 107,
    "Label12_7": 108,
    "Label12_8": 178,
    "Label12_9": 179,
    "Label13": 112,
    "Label13_1": 213,
    "Label2": 54,
    "Label2_2": 130,
    "Label4": 4,
    "Label4_1": 18,
    "Label4_2": 119,
    "Label5": 59,
    "Label5_1": 28,
    "Label5_10": 145,
    "Label5_11": 146,
    "Label5_12": 158,
    "Label5_13": 177,
    "Label5_14": 187,
    "Label5_15": 197,
    "Label5_16": 207,
    "Label5_17": 62,
    "Label5_2": 76,
    "Label5_3": 86,
    "Label5_4": 44,
    "Label5_5": 45,
    "Label5_6": 33,
    "Label5_7": 96,
    "Label5_8": 106,
    "Label5_9": 126,
    "Label6": 41,
    "Label6_1": 70,
    "Label6_2": 136,
    "Label6_3": 171,
    "Last Name_DataCard1": 235,
    "Microsoft Profile": 39,
    "Microsoft Profile_DataCard1": 225,
    "Name_1": 30,
    "Name_2": 129,
    "Primary Alignment": 23,
    "Primary Alignment_1": 125,
    "Profesional Experience": 23,
    "Profile box": 29,
    "Profile box_1": 128,
    "Profile_DataCard1": 255,
    "ProfilePic_2": 25,
    "ProfilePic_3": 127,
    "Qualification 1_DataCard1": 320,
    "Qualification 2_DataCard1": 325,
    "Qualification 3_DataCard1": 330,
    "Rectangle2": 37,
    "Rectangle2_1": 67,
    "Rectangle2_2": 133,
    "Rectangle2_3": 168,
    "Role Title_DataCard1": 240,
    "RoleTitle": 24,
    "RoleTitle_1": 124,
    "Screen1": 75,
    "Search CV Button": 11,
    "Skill 1 Evidence _DataCard1": 265,
    "Skill 1_DataCard1": 260,
    "Skill 2 Evidence_DataCard1": 275,
    "Skill 2_DataCard1": 270,
    "Skill 3 Evidence_DataCard1": 285,
    "Skill 3_DataCard1": 280,
    "Skill 4 Evidence_DataCard1": 310,
    "Skill 4_DataCard1": 290,
    "Skill 5 Evidence_DataCard1": 305,
    "Skill 5_DataCard1": 295,
    "Skill 6 Evidence_DataCard1": 315,
    "Skill 6_DataCard1": 300,
    "Skills Competancies & Qualifications": 293,
    "StarVisible1": 221,
    "StarVisible10": 266,
    "StarVisible11": 271,
    "StarVisible12": 276,
    "StarVisible13": 281,
    "StarVisible14": 286,
    "StarVisible15": 291,
    "StarVisible16": 296,
    "StarVisible17": 301,
    "StarVisible18": 306,
    "StarVisible19": 311,
    "StarVisible2": 226,
    "StarVisible20": 316,
    "StarVisible21": 321,
    "StarVisible22": 326,
    "StarVisible23": 331,
    "StarVisible24": 336,
    "StarVisible25": 341,
    "StarVisible26": 346,
    "StarVisible27": 351,
    "StarVisible28": 356,
    "StarVisible29": 361,
    "StarVisible3": 231,
    "StarVisible30": 366,
    "StarVisible31": 371,
    "StarVisible32": 376,
    "StarVisible33": 381,
    "StarVisible34": 386,
    "StarVisible35": 391,
    "StarVisible36": 396,
    "StarVisible37": 401,
    "StarVisible38": 406,
    "StarVisible39": 411,
    "StarVisible4": 236,
    "StarVisible40": 416,
    "StarVisible41": 421,
    "StarVisible42": 426,
    "StarVisible43": 431,
    "StarVisible5": 241,
    "StarVisible6": 246,
    "StarVisible7": 251,
    "StarVisible8": 256,
    "StarVisible9": 261,
    "SuccessScreen": 320,
    "TextInput2_10": 162,
    "TextInput2_11": 164,
    "TextInput2_6": 148,
    "TextInput2_7": 151,
    "TextInput2_8": 154,
    "TextInput2_9": 159,
    "TextInput3_10": 163,
    "TextInput3_11": 165,
    "TextInput3_6": 149,
    "TextInput3_7": 152,
    "TextInput3_8": 155,
    "TextInput3_9": 160,
    "TextInput4_3": 147,
    "TextInput4_4": 150,
    "TextInput4_5": 153,
    "TextInput6_1": 161,
    "TextInput7_3": 111,
    "TextInput7_4": 212,
    "TextInput8_10": 104,
    "TextInput8_11": 105,
    "TextInput8_12": 204,
    "TextInput8_13": 205,
    "TextInput8_14": 206,
    "TextInput8_9": 103,
    "Title_DataCard1": 220,
    "Update": 321,
    "Update CV Button": 6,
    "Update_Profesional Experience": 337,
    "Update_Skills Competancies & Qualifications": 389,
    "View CV Button": 14,
    "Welcome": 425
  },
  "ResourcesJsonIndices": {
    "Image-Cap squiggle": 1,
    "Image-Logo Blue": 2,
    "Image-Picture5": 3,
    "Image-SampleImage": 0,
    "Image-Screenshot 2024-03-04 120003": 4,
    "Image-White Logo Capgemini Invent": 5
  },
  "RuleScreenIdWithoutScreen": {},
  "TemplateVersions": {},
  "VolatileProperties": {
    "AnalysisLoadTime": 2.4622025,
    "ControlCount": {
      "6b01bf047f29498a89aa71ff084a0b2f": 1,
      "attachments": 1,
      "button": 32,
      "checkbox": 2,
      "combobox": 7,
      "datepicker": 22,
      "dropdown": 4,
      "form": 1,
      "gallery": 2,
      "galleryTemplate": 2,
      "group": 10,
      "groupContainer": 8,
      "icon": 14,
      "image": 15,
      "label": 180,
      "rectangle": 7,
      "screen": 9,
      "text": 86,
      "typedDataCard": 43
    },
    "DeserializationLoadTime": 3.2637892
  },
  "WasLocalDatabaseReferencesEmpty": true
}